README.rst
setup.cfg
setup.py
django_smart_save.egg-info/PKG-INFO
django_smart_save.egg-info/SOURCES.txt
django_smart_save.egg-info/dependency_links.txt
django_smart_save.egg-info/not-zip-safe
django_smart_save.egg-info/top_level.txt
smart_save/__init__.py
smart_save/models.py