Metadata-Version: 1.1
Name: django-smart-save
Version: 0.0.11
Summary: Automatically validates when you call your model’s save()
Home-page: https://github.com/danielgatis/django-smart-save
Author: Daniel Gatis Carrazzoni
Author-email: danielgatis@gmail.com
License: BSD License
Platform: OS Independent
Classifier: Development Status :: 4 - Beta
Classifier: Environment :: Web Environment
Classifier: Intended Audience :: Developers
Classifier: License :: OSI Approved :: BSD License
Classifier: Operating System :: OS Independent
Classifier: Programming Language :: Python
Classifier: Programming Language :: Python :: 2.6
Classifier: Programming Language :: Python :: 2.7
Classifier: Programming Language :: Python :: 3.3
Classifier: Programming Language :: Python :: 3.4
Classifier: Framework :: Django
